neuroptimiser/__init__.py
neuroptimiser/solvers.py
neuroptimiser/utils.py
neuroptimiser/core/__init__.py
neuroptimiser/core/models.py
neuroptimiser/core/processes.py
neuroptimiser-1.0.2.dist-info/licenses/LICENSE
neuroptimiser-1.0.2.dist-info/METADATA
neuroptimiser-1.0.2.dist-info/WHEEL
neuroptimiser-1.0.2.dist-info/top_level.txt
neuroptimiser-1.0.2.dist-info/RECORD
