Metadata-Version: 2.4
Name: neuroptimiser
Version: 1.0.2
Summary: A modular and asynchronous framework for neuromorphic optimisation using spike-driven metaheuristics and heuristic-controlled spiking dynamics.
Author-email: Jorge Mario Cruz-Duarte <jorge.cruz-duarte@univ-lille.fr>, El-Ghazali Talbi <el-ghazali.talbi@univ-lille.fr>
License-Expression: MIT
Project-URL: Homepage, https://neuroptimiser.github.io
Project-URL: Documentation, https://neuroptimiser.github.io
Project-URL: Source, https://github.com/neuroptimiser/neuroptimiser
Keywords: neuromorphic,spiking,optimisation,lava-nc
Classifier: Programming Language :: Python :: 3
Classifier: Operating System :: OS Independent
Requires-Python: >=3.10
License-File: LICENSE
Requires-Dist: ipython>=8.31.0
Requires-Dist: matplotlib>=3.10.0
Requires-Dist: numpy>=1.25.0
Requires-Dist: networkx>=2.8
Requires-Dist: cmaes>=0.11.1
Requires-Dist: torch>=2.5.1
Requires-Dist: scipy>=1.15.3
Requires-Dist: graphviz>=0.20.3
Requires-Dist: tikzpy>=0.0.4
Requires-Dist: lava-nc>=0.10.0
Requires-Dist: seaborn>=0.13.2
Requires-Dist: schema>=0.7.7
Requires-Dist: notebook>=7.4.5
Provides-Extra: dev
Requires-Dist: pytest>=8.3.4; extra == "dev"
Requires-Dist: build>=1.0.0; extra == "dev"
Requires-Dist: twine>=4.0.2; extra == "dev"
Requires-Dist: cocopp>=2.7.3; extra == "dev"
Requires-Dist: coco-experiment>=2.8.1; extra == "dev"
Requires-Dist: ioh>=0.3.18; extra == "dev"
Provides-Extra: docs
Requires-Dist: sphinx>=8.1.3; extra == "docs"
Requires-Dist: sphinx-autodoc-typehints>=3.0.1; extra == "docs"
Requires-Dist: sphinx-rtd-theme>=3.0.2; extra == "docs"
Requires-Dist: sphinxcontrib-napoleon>=0.7; extra == "docs"
Requires-Dist: furo>=2024.8.6; extra == "docs"
Requires-Dist: myst-nb>=1.2.0; extra == "docs"
Requires-Dist: sphinx-copybutton>=0.5.2; extra == "docs"
Requires-Dist: sphinx-panels>=0.4.1; extra == "docs"
Requires-Dist: sphinx-design>=0.6.1; extra == "docs"
Dynamic: license-file
